{
  "openapi": "3.1.0",
  "info": {
    "title": "Uniflow API",
    "version": "1.0.0",
    "description": "API for Uniflow - Authentication, Notes, Queue System, and more."
  },
  "servers": [
    {
      "url": "http://localhost:3000",
      "description": "Local dev server"
    }
  ],
  "paths": {
    "/health": {
      "get": {
        "summary": "Health check",
        "description": "Check if the API and database are running",
        "responses": {
          "200": {
            "description": "API is healthy",
            "content": {
              "application/json": {
                "schema": {
                  "type": "object",
                  "properties": {
                    "status": { "type": "string", "example": "healthy" },
                    "message": { "type": "string" },
                    "database": { "type": "string", "example": "connected" },
                    "userCount": { "type": "number" },
                    "timestamp": { "type": "string", "format": "date-time" }
                  }
                }
              }
            }
          },
          "500": {
            "description": "API is unhealthy",
            "content": {
              "application/json": {
                "schema": {
                  "type": "object",
                  "properties": {
                    "status": { "type": "string", "example": "unhealthy" },
                    "message": { "type": "string" },
                    "database": { "type": "string", "example": "disconnected" },
                    "error": { "type": "string" },
                    "timestamp": { "type": "string", "format": "date-time" }
                  }
                }
              }
            }
          }
        }
      }
    },
    "/auth/signup": {
      "post": {
        "summary": "Register a new user",
        "requestBody": {
          "required": true,
          "content": {
            "application/json": {
              "schema": {
                "type": "object",
                "properties": {
                  "email": { "type": "string", "format": "email" },
                  "password": { "type": "string", "minLength": 6 },
                  "name": { "type": "string" }
                },
                "required": ["email", "password"]
              }
            }
          }
        },
        "responses": {
          "201": { "description": "User created" },
          "400": { "description": "Validation error" }
        }
      }
    },
    "/auth/signin": {
      "post": {
        "summary": "Login with email and password",
        "requestBody": {
          "required": true,
          "content": {
            "application/json": {
              "schema": {
                "type": "object",
                "properties": {
                  "email": { "type": "string", "format": "email" },
                  "password": { "type": "string" }
                },
                "required": ["email", "password"]
              }
            }
          }
        },
        "responses": {
          "200": { "description": "Login successful, returns JWT token" },
          "401": { "description": "Invalid credentials" }
        }
      }
    },
    "/profile/me": {
      "get": {
        "summary": "Get current user profile",
        "security": [{ "bearerAuth": [] }],
        "responses": {
          "200": {
            "description": "User profile",
            "content": {
              "application/json": {
                "schema": {
                  "type": "object",
                  "properties": {
                    "userId": { "type": "string" },
                    "email": { "type": "string" },
                    "school": { "type": "string" },
                    "department": { "type": "string" },
                    "level": { "type": "string" },
                    "bio": { "type": "string" },
                    "createdAt": { "type": "string", "format": "date-time" }
                  }
                }
              }
            }
          },
          "401": { "description": "Unauthorized" },
          "404": { "description": "Profile not found" }
        }
      },
      "put": {
        "summary": "Update current user profile",
        "security": [{ "bearerAuth": [] }],
        "requestBody": {
          "required": true,
          "content": {
            "application/json": {
                              "schema": {
                  "type": "object",
                  "properties": {
                    "name": { "type": "string" },
                    "profilePicture": { "type": "string" },
                    "themeColor": { "type": "string" },
                    "darkMode": { "type": "boolean" },
                    "school": { "type": "string" },
                    "department": { "type": "string" },
                    "level": { "type": "string" },
                    "academicYear": { "type": "string" },
                    "subjects": { "type": "array", "items": { "type": "string" } },
                    "bio": { "type": "string" },
                    "notificationSettings": {
                      "type": "object",
                      "properties": {
                        "pushNotifications": { "type": "boolean" },
                        "emailNotifications": { "type": "boolean" },
                        "studyReminders": { "type": "boolean" },
                        "taskReminders": { "type": "boolean" },
                        "motivationalMessages": { "type": "boolean" }
                      }
                    },
                    "studyGoals": {
                      "type": "object",
                      "properties": {
                        "dailyHours": { "type": "number" },
                        "weeklyHours": { "type": "number" },
                        "subjects": { "type": "object" }
                      }
                    },
                    "preferences": {
                      "type": "object",
                      "properties": {
                        "focusModeDuration": { "type": "number" },
                        "breakDuration": { "type": "number" },
                        "autoStartBreaks": { "type": "boolean" },
                        "backgroundMusic": { "type": "boolean" }
                      }
                    }
                  }
                }
            }
          }
        },
        "responses": {
          "200": {
            "description": "Profile updated successfully",
            "content": {
              "application/json": {
                "schema": {
                  "type": "object",
                  "properties": {
                    "userId": { "type": "string" },
                    "email": { "type": "string" },
                    "school": { "type": "string" },
                    "department": { "type": "string" },
                    "level": { "type": "string" },
                    "bio": { "type": "string" },
                    "createdAt": { "type": "string", "format": "date-time" }
                  }
                }
              }
            }
          },
          "401": { "description": "Unauthorized" },
          "404": { "description": "Profile not found" }
        }
      },
      "delete": {
        "summary": "Delete current user profile",
        "security": [{ "bearerAuth": [] }],
        "responses": {
          "200": {
            "description": "Profile deleted successfully",
            "content": {
              "application/json": {
                "schema": {
                  "type": "object",
                  "properties": {
                    "message": { "type": "string" }
                  }
                }
              }
            }
          },
          "401": { "description": "Unauthorized" },
          "404": { "description": "Profile not found" }
        }
      }
    }
  },
  "components": {
    "securitySchemes": {
      "bearerAuth": {
        "type": "http",
        "scheme": "bearer",
        "bearerFormat": "JWT"
      }
    }
  }
}
